redwoodresearchwidgets/__init__.py
redwoodresearchwidgets/main.py
redwoodresearchwidgets-0.0.0.dist-info/LICENSE.txt
redwoodresearchwidgets-0.0.0.dist-info/METADATA
redwoodresearchwidgets-0.0.0.dist-info/WHEEL
redwoodresearchwidgets-0.0.0.dist-info/top_level.txt
redwoodresearchwidgets-0.0.0.dist-info/RECORD
